Metadata-Version: 1.1
Name: bamboo-api-v2
Version: 0.0.1
Summary: Bamboo API Client v2
Home-page: https://github.com/adamar/python-bamboo-api
Author: UNKNOWN
Author-email: UNKNOWN
License: MIT
Keywords: api bamboo rest api client
Platform: UNKNOWN
Classifier: Development Status :: 3 - Alpha
Classifier: Environment :: Console
Classifier: Intended Audience :: End Users/Desktop
Classifier: License :: OSI Approved :: MIT License
Classifier: Operating System :: Unix
Classifier: Programming Language :: Python :: 3
